setup.py
c_progress_bar/__init__.py
c_progress_bar/setup.py
c_progress_bar/test.py
c_progress_bar.egg-info/PKG-INFO
c_progress_bar.egg-info/SOURCES.txt
c_progress_bar.egg-info/dependency_links.txt
c_progress_bar.egg-info/top_level.txt