Metadata-Version: 1.0
Name: c-progress-bar
Version: 0.0.3
Summary: show progress bar
Home-page: https://www.cnblogs.com/Evan-fanfan/
Author: evanyang
Author-email: lightyiyi@qq.com
License: MIT License
Platform: UNKNOWN
